rnakinetics/ODEsolver.py
rnakinetics/__init__.py
RNAkinetics-0.2.4.dist-info/LICENSE
RNAkinetics-0.2.4.dist-info/METADATA
RNAkinetics-0.2.4.dist-info/WHEEL
RNAkinetics-0.2.4.dist-info/top_level.txt
RNAkinetics-0.2.4.dist-info/RECORD
