Metadata-Version: 2.1
Name: RNAkinetics
Version: 0.2.4
Summary: Biological prior guided single-cell kinetics inference.
Home-page: https://github.com/poseidonchan/scKinetics
Author: Yanshuo Chen
Author-email: poseidonchan@icloud.com
License: MIT license
Platform: Linux
Requires-Python: >=3.9
License-File: LICENSE
Requires-Dist: diffrax (==0.4.1)
Requires-Dist: jax (>=0.4.13)
Requires-Dist: equinox (>=0.10.11)
Requires-Dist: optax
Requires-Dist: anndata (>=0.7.6)
Requires-Dist: tqdm
Requires-Dist: numpy
